causalite/__init__.py
causalite/causal_models.py
causalite/exceptions.py
causalite/node_models.py
causalite-0.1.0.dist-info/LICENSE
causalite-0.1.0.dist-info/METADATA
causalite-0.1.0.dist-info/WHEEL
causalite-0.1.0.dist-info/top_level.txt
causalite-0.1.0.dist-info/RECORD
