Metadata-Version: 2.1
Name: causalite
Version: 0.1.0
Summary: Python package for defining and interacting with causal models, with a particular emphasis on Structural Causal Models
Author-email: Anil Rao <anilwrao.projects@gmail.com>
License: Apache-2.0
Project-URL: Homepage, https://github.com/awrao/causalite
Keywords: causality
Classifier: License :: OSI Approved :: Apache Software License
Classifier: Programming Language :: Python :: 3
Requires-Python: >=3.9
License-File: LICENSE
Requires-Dist: numpy>=1.24.3
Requires-Dist: scipy>=1.10.1
Requires-Dist: pandas>=1.5.3
